MANIFEST.in
README.txt
ez_setup.py
setup.py
examples/allocation.py
examples/external_module.py
examples/gpu.py
examples/heat_equation.py
examples/map.py
examples/map_async.py
examples/map_dependencies.py
examples/map_lambda.py
examples/map_shared.py
examples/maximize.py
examples/maximize_class.py
examples/maximize_groups.py
examples/maximize_matrix.py
examples/monte_carlo.py
examples/resources.py
playdoh/__init__.py
playdoh/asyncjobhandler.py
playdoh/baserpc.py
playdoh/cache.py
playdoh/connection.py
playdoh/debugtools.py
playdoh/filetransfer.py
playdoh/gputools.py
playdoh/interface.py
playdoh/pool.py
playdoh/resources.py
playdoh/rpc.py
playdoh/synchandler.py
playdoh/userpref.py
playdoh.egg-info/PKG-INFO
playdoh.egg-info/SOURCES.txt
playdoh.egg-info/dependency_links.txt
playdoh.egg-info/entry_points.txt
playdoh.egg-info/requires.txt
playdoh.egg-info/top_level.txt
playdoh/codehandler/__init__.py
playdoh/codehandler/cloudpickle.py
playdoh/codehandler/codedependency.py
playdoh/codehandler/codehandler.py
playdoh/codehandler/xrange_helper.py
playdoh/optimization/__init__.py
playdoh/optimization/algorithm.py
playdoh/optimization/cma_es.py
playdoh/optimization/cma_utils.py
playdoh/optimization/de.py
playdoh/optimization/de_utils.py
playdoh/optimization/ga.py
playdoh/optimization/optimization.py
playdoh/optimization/pso.py
playdoh/scripts/__init__.py
playdoh/scripts/client_gui.py
playdoh/scripts/console.py
playdoh/scripts/open.py
playdoh/scripts/openrestart.py