Metadata-Version: 1.0
Name: playdoh
Version: 0.3
Summary: Open-source library for distributing computations over multiple cores and machines
Home-page: http://code.google.com/p/playdoh/
Author: Cyrille Rossant, Bertrand Fontaine, Dan F. M. Goodman
Author-email: Cyrille.Rossant at ens.fr
License: UNKNOWN
Download-URL: http://code.google.com/p/playdoh/downloads/list
Platform: UNKNOWN
Classifier: Development Status :: 4 - Beta
Classifier: Intended Audience :: Science/Research
Classifier: License :: OSI Approved :: GNU General Public License (GPL)
Classifier: Natural Language :: English
Classifier: Operating System :: OS Independent
Classifier: Programming Language :: Python
Classifier: Topic :: Scientific/Engineering
